cloudarchive/__init__.py
cloudarchive/core.py
cloudarchive/__metadata__/LICENSE
cloudarchive/__metadata__/README.md
cloudarchive/__metadata__/__init__.py
cloudarchive/__metadata__/requirements.txt
cloudarchive-1.0.0.dist-info/METADATA
cloudarchive-1.0.0.dist-info/WHEEL
cloudarchive-1.0.0.dist-info/top_level.txt
cloudarchive-1.0.0.dist-info/RECORD
