Metadata-Version: 2.1
Name: cloudarchive
Version: 1.0.0
Summary: Internet Archive client. DO NOT BOTHER UPLOAD WAREZ OR ENCRYPTED BINARY. IA would just flag and soft ban your account if you cannot explain what is the exact purpose of archiving that data.
Home-page: https://github.com/foxe6/
Author: f̣ộx̣ệ6
Author-email: foxe6@protonmail.com
License: AGPL-3.0
Project-URL: Sourcecode, https://github.com/foxe6/cloudarchive
Project-URL: Documentation, https://github.com/foxe6/cloudarchive/blob/master/test
Project-URL: Example, https://github.com/foxe6/cloudarchive/blob/master/cloudarchive/example
Project-URL: Issues, https://github.com/foxe6/cloudarchive/issues
Project-URL: Funding, https://paypal.me/foxe6
Project-URL: Say Thanks!, https://saythanks.io/to/foxe6
Keywords: file cloud internet archive host
Platform: UNKNOWN
Classifier: Programming Language :: Python :: 3.9
Classifier: Topic :: Utilities
Classifier: Natural Language :: English
Classifier: Intended Audience :: Developers
Classifier: License :: OSI Approved :: GNU Affero General Public License v3
Classifier: Operating System :: MacOS
Classifier: Operating System :: POSIX
Classifier: Operating System :: Microsoft :: Windows :: Windows 10
Classifier: Development Status :: 5 - Production/Stable
Requires-Python: >=3
Requires-Dist: lxml (>=0.0.1)
Requires-Dist: requests (>=0.0.1)
